FPL4/__init__.py
FPL4/primo.py
FPL4-1.0.dist-info/LICENSE
FPL4-1.0.dist-info/METADATA
FPL4-1.0.dist-info/WHEEL
FPL4-1.0.dist-info/top_level.txt
FPL4-1.0.dist-info/RECORD
