Metadata-Version: 2.1
Name: FPL4
Version: 1.0
Summary: A tool to perform mathematical operations.
Home-page: UNKNOWN
Author: Alejandro Nicol
Author-email: alex.niicol@gmail.com
License: GNU GPLv3
Keywords: calcular numeros primos mathematical operations
Platform: UNKNOWN
Classifier: Development Status :: 4 - Beta
Classifier: Intended Audience :: Developers
Classifier: Topic :: Utilities
Classifier: License :: OSI Approved :: GNU General Public License v3 (GPLv3)
Classifier: Programming Language :: Python :: 3
Classifier: Operating System :: OS Independent
License-File: LICENSE
